Classfile /Users/BMW/Documents/Git/ExtendJ-Mapper/test_files/J18.class
  Last modified 11-May-2018; size 4987 bytes
  MD5 checksum 9f926ee36b59ce9b67a8549fc3406a6b
  Compiled from "J18.java"
class J18 extends Java
  minor version: 0
  major version: 49
  flags: ACC_SUPER
Constant pool:
    #1 = Utf8               J18
    #2 = Class              #1            // J18
    #3 = Utf8               Java
    #4 = Class              #3            // Java
    #5 = Utf8               name
    #6 = Utf8               Ljava/lang/String;
    #7 = Utf8               Signature
    #8 = Utf8               type
    #9 = Utf8               LTypeOfLanguage;
   #10 = Utf8               $assertiosDisabled
   #11 = Utf8               Z
   #12 = Utf8               <init>
   #13 = Utf8               (Ljava/lang/String;)V
   #14 = Utf8               this
   #15 = Utf8               LJ18;
   #16 = Utf8               ()V
   #17 = NameAndType        #12:#16       // "<init>":()V
   #18 = Methodref          #4.#17        // Java."<init>":()V
   #19 = NameAndType        #5:#6         // name:Ljava/lang/String;
   #20 = Fieldref           #2.#19        // J18.name:Ljava/lang/String;
   #21 = Utf8               TypeOfLanguage
   #22 = Class              #21           // TypeOfLanguage
   #23 = Utf8               IMPERATIVE
   #24 = NameAndType        #23:#9        // IMPERATIVE:LTypeOfLanguage;
   #25 = Fieldref           #22.#24       // TypeOfLanguage.IMPERATIVE:LTypeOfLanguage;
   #26 = NameAndType        #8:#9         // type:LTypeOfLanguage;
   #27 = Fieldref           #2.#26        // J18.type:LTypeOfLanguage;
   #28 = Utf8               Code
   #29 = Utf8               LineNumberTable
   #30 = Utf8               PositionTable
   #31 = Utf8               LocalVariableTable
   #32 = Utf8               Exceptions
   #33 = Utf8               assertion
   #34 = Utf8               (I)I
   #35 = Utf8               x
   #36 = Utf8               I
   #37 = Utf8               a
   #38 = NameAndType        #10:#11       // $assertiosDisabled:Z
   #39 = Fieldref           #2.#38        // J18.$assertiosDisabled:Z
   #40 = Utf8               java/lang/AssertionError
   #41 = Class              #40           // java/lang/AssertionError
   #42 = Methodref          #41.#17       // java/lang/AssertionError."<init>":()V
   #43 = Utf8               loops
   #44 = Utf8               ([I)I
   #45 = Utf8               items
   #46 = Utf8               [I
   #47 = Utf8               counter
   #48 = Utf8               i
   #49 = Utf8               m
   #50 = Utf8               Ljava/util/ArrayList;
   #51 = Utf8               java/util/ArrayList
   #52 = Class              #51           // java/util/ArrayList
   #53 = Methodref          #52.#17       // java/util/ArrayList."<init>":()V
   #54 = Utf8               java/lang/Integer
   #55 = Class              #54           // java/lang/Integer
   #56 = Utf8               valueOf
   #57 = Utf8               (I)Ljava/lang/Integer;
   #58 = NameAndType        #56:#57       // valueOf:(I)Ljava/lang/Integer;
   #59 = Methodref          #55.#58       // java/lang/Integer.valueOf:(I)Ljava/lang/Integer;
   #60 = Utf8               add
   #61 = Utf8               (Ljava/lang/Object;)Z
   #62 = NameAndType        #60:#61       // add:(Ljava/lang/Object;)Z
   #63 = Methodref          #52.#62       // java/util/ArrayList.add:(Ljava/lang/Object;)Z
   #64 = Utf8               J18$1
   #65 = Class              #64           // J18$1
   #66 = Utf8               (LJ18;)V
   #67 = NameAndType        #12:#66       // "<init>":(LJ18;)V
   #68 = Methodref          #65.#67       // J18$1."<init>":(LJ18;)V
   #69 = Utf8               java/util/function/Consumer
   #70 = Class              #69           // java/util/function/Consumer
   #71 = Utf8               forEach
   #72 = Utf8               (Ljava/util/function/Consumer;)V
   #73 = NameAndType        #71:#72       // forEach:(Ljava/util/function/Consumer;)V
   #74 = Methodref          #52.#73       // java/util/ArrayList.forEach:(Ljava/util/function/Consumer;)V
   #75 = Utf8               bitwise
   #76 = Utf8               b
   #77 = Utf8               D
   #78 = Utf8               ifStatements
   #79 = Utf8               ()Z
   #80 = Utf8               s
   #81 = Utf8               hello
   #82 = String             #81           // hello
   #83 = Utf8               java/lang/Object
   #84 = Class              #83           // java/lang/Object
   #85 = Utf8               hashCode
   #86 = Utf8               ()I
   #87 = NameAndType        #85:#86       // hashCode:()I
   #88 = Methodref          #84.#87       // java/lang/Object.hashCode:()I
   #89 = Utf8               equals
   #90 = NameAndType        #89:#61       // equals:(Ljava/lang/Object;)Z
   #91 = Methodref          #84.#90       // java/lang/Object.equals:(Ljava/lang/Object;)Z
   #92 = Utf8               world
   #93 = String             #92           // world
   #94 = Utf8               ic
   #95 = Utf8               LJ18$InnerClass;
   #96 = Utf8               J18$InnerClass
   #97 = Class              #96           // J18$InnerClass
   #98 = Utf8               (LJ18;I)V
   #99 = NameAndType        #12:#98       // "<init>":(LJ18;I)V
  #100 = Methodref          #97.#99       // J18$InnerClass."<init>":(LJ18;I)V
  #101 = Utf8               Ljava/lang/Integer;
  #102 = Utf8               exceptionThrower
  #103 = Utf8               java/lang/Exception
  #104 = Class              #103          // java/lang/Exception
  #105 = Utf8               A chained Exception has been thrown.
  #106 = String             #105          // A chained Exception has been thrown.
  #107 = NameAndType        #12:#13       // "<init>":(Ljava/lang/String;)V
  #108 = Methodref          #104.#107     // java/lang/Exception."<init>":(Ljava/lang/String;)V
  #109 = Utf8               java/lang/IndexOutOfBoundsException
  #110 = Class              #109          // java/lang/IndexOutOfBoundsException
  #111 = Utf8               <clinit>
  #112 = Utf8               java/lang/Class
  #113 = Class              #112          // java/lang/Class
  #114 = Utf8               desiredAssertionStatus
  #115 = NameAndType        #114:#79      // desiredAssertionStatus:()Z
  #116 = Methodref          #113.#115     // java/lang/Class.desiredAssertionStatus:()Z
  #117 = Utf8               InnerClasses
  #118 = Utf8               InnerClass
  #119 = Utf8               SourceFile
  #120 = Utf8               J18.java
  #121 = Utf8               This class file was generated by node 131
{
  static final boolean $assertiosDisabled;
    descriptor: Z
    flags: ACC_STATIC, ACC_FINAL, ACC_SYNTHETIC

  public J18(java.lang.String) throws ;
    descriptor: (Ljava/lang/String;)V
    flags: ACC_PUBLIC
    Code:
      stack=2, locals=3, args_size=2
         0: aload_0
         1: invokespecial #18                 // Method Java."<init>":()V
         4: aload_0
         5: pop
         6: aload_1
         7: putstatic     #20                 // Field name:Ljava/lang/String;
        10: aload_0
        11: getstatic     #25                 // Field TypeOfLanguage.IMPERATIVE:LTypeOfLanguage;
        14: putfield      #27                 // Field type:LTypeOfLanguage;
        17: return
      LineNumberTable:
        line 29: 4
        line 30: 10
Error: unknown attribute
        PositionTable: length = 0x60
         00 04 00 1D 00 05 00 1D 00 08 00 AF 00 05 00 1D
         00 0A 00 1D 00 0D 02 BA 00 06 00 1D 00 11 00 1D
         00 14 02 BB 00 07 00 1D 00 05 00 1D 00 14 00 AD
         00 0A 00 1E 00 05 00 1E 00 08 00 B5 00 0B 00 1E
         00 20 00 1E 00 29 02 BC 00 0E 00 1E 00 05 00 1E
         00 29 00 B3 00 11 00 1C 00 05 00 1F 00 05 00 9F

      LocalVariableTable:
        Start  Length  Slot  Name   Signature
            0      18     0  this   LJ18;
            0      18     1  name   Ljava/lang/String;
    Exceptions:
      throws

  public int assertion(int) throws ;
    descriptor: (I)I
    flags: ACC_PUBLIC
    Exceptions:
      throws
    Code:
      stack=2, locals=5, args_size=2
         0: iconst_3
         1: istore_3
         2: iload_3
         3: iconst_5
         4: iadd
         5: istore_3
         6: getstatic     #39                 // Field $assertiosDisabled:Z
         9: ifne          26
        12: iload_3
        13: bipush        8
        15: if_icmpeq     26
        18: new           #41                 // class java/lang/AssertionError
        21: dup
        22: invokespecial #42                 // Method java/lang/AssertionError."<init>":()V
        25: athrow
        26: iload_1
        27: iload_3
        28: imul
        29: ireturn
      LineNumberTable:
        line 34: 0
        line 35: 2
        line 37: 26
Error: unknown attribute
        PositionTable: length = 0x9C
         00 00 00 22 00 11 00 22 00 11 02 BD 00 01 00 22
         00 0D 00 22 00 11 00 CE 00 02 00 23 00 0B 00 23
         00 0B 02 BE 00 03 00 23 00 0D 00 23 00 0D 02 BF
         00 04 00 23 00 0B 00 23 00 0D 00 D6 00 05 00 23
         00 07 00 23 00 0D 00 D4 00 0C 00 24 00 0E 00 24
         00 0E 02 C1 00 0D 00 24 00 13 00 24 00 13 02 C2
         00 0F 00 24 00 0E 00 24 00 13 02 C3 00 1A 00 25
         00 10 00 25 00 10 02 C6 00 1B 00 25 00 14 00 25
         00 14 02 C7 00 1C 00 25 00 10 00 25 00 14 00 E1
         00 1D 00 25 00 09 00 25 00 15 00 DF
      LocalVariableTable:
        Start  Length  Slot  Name   Signature
            0      30     0  this   LJ18;
            0      30     1     x   I
            0      30     3     a   I

  public int loops(int...) throws ;
    descriptor: ([I)I
    flags: ACC_PUBLIC, ACC_VARARGS
    Exceptions:
      throws
    Code:
      stack=4, locals=9, args_size=2
         0: iconst_0
         1: istore_3
         2: iconst_0
         3: istore        4
         5: iload         4
         7: bipush        10
         9: if_icmpgt     25
        12: iload_3
        13: iconst_1
        14: iadd
        15: istore_3
        16: iload         4
        18: iconst_1
        19: iadd
        20: istore        4
        22: goto          5
        25: iload_3
        26: iconst_5
        27: if_icmple     37
        30: iload_3
        31: iconst_m1
        32: iadd
        33: istore_3
        34: goto          25
        37: iload_3
        38: iconst_1
        39: iadd
        40: istore_3
        41: iload_3
        42: bipush        10
        44: if_icmplt     37
        47: iload_3
        48: iconst_m1
        49: iadd
        50: istore_3
        51: iload_3
        52: iconst_1
        53: iadd
        54: istore_3
        55: iload_3
        56: iconst_1
        57: isub
        58: istore_3
        59: iload_3
        60: iconst_1
        61: imul
        62: istore_3
        63: iload_3
        64: iconst_1
        65: idiv
        66: istore_3
        67: new           #52                 // class java/util/ArrayList
        70: dup
        71: invokespecial #53                 // Method java/util/ArrayList."<init>":()V
        74: astore        4
        76: aload_1
        77: astore        5
        79: iconst_0
        80: istore        6
        82: iload         6
        84: aload         5
        86: arraylength
        87: if_icmpge     114
        90: aload         5
        92: iload         6
        94: iaload
        95: istore        7
        97: aload         4
        99: iload         7
       101: invokestatic  #59                 // Method java/lang/Integer.valueOf:(I)Ljava/lang/Integer;
       104: invokevirtual #63                 // Method java/util/ArrayList.add:(Ljava/lang/Object;)Z
       107: pop
       108: iinc          6, 1
       111: goto          82
       114: aload         4
       116: new           #65                 // class J18$1
       119: dup
       120: aload_0
       121: invokespecial #68                 // Method J18$1."<init>":(LJ18;)V
       124: checkcast     #70                 // class java/util/function/Consumer
       127: invokevirtual #74                 // Method java/util/ArrayList.forEach:(Ljava/util/function/Consumer;)V
       130: iload_3
       131: ireturn
      LineNumberTable:
        line 48: 0
        line 49: 2
        line 49: 2
        line 50: 12
        line 49: 16
        line 53: 25
        line 54: 30
        line 55: 34
        line 58: 37
        line 59: 37
        line 61: 47
        line 63: 51
        line 64: 55
        line 65: 59
        line 66: 63
        line 68: 67
        line 71: 97
        line 74: 114
        line 76: 130
Error: unknown attribute
        PositionTable: length = 0x360
         00 00 00 30 00 12 00 30 00 12 02 C8 00 01 00 30
         00 08 00 30 00 12 01 21 00 02 00 31 00 11 00 31
         00 11 02 C9 00 03 00 31 00 0D 00 31 00 11 01 2D
         00 05 00 31 00 14 00 31 00 14 02 CA 00 07 00 31
         00 19 00 31 00 1A 02 CB 00 09 00 31 00 14 00 31
         00 1A 01 33 00 0C 00 32 00 07 00 32 00 0D 02 CC
         00 0D 00 32 00 05 00 32 00 0D 01 3D 00 0E 00 32
         00 05 00 32 00 0D 01 3D 00 0F 00 32 00 05 00 32
         00 0D 01 3D 00 10 00 31 00 1D 00 31 00 1D 02 CD
         00 12 00 31 00 1D 00 31 00 1F 01 38 00 13 00 31
         00 1D 00 31 00 1F 01 38 00 14 00 31 00 1D 00 31
         00 1F 01 38 00 19 00 35 00 0B 00 35 00 11 02 CE
         00 1A 00 35 00 15 00 35 00 15 02 CF 00 1B 00 35
         00 0B 00 35 00 15 01 40 00 1E 00 36 00 05 00 36
         00 0B 02 D0 00 1F 00 36 00 05 00 36 00 0D 01 46
         00 20 00 36 00 05 00 36 00 0D 01 46 00 21 00 36
         00 05 00 36 00 0D 01 46 00 25 00 3B 00 05 00 3B
         00 0B 02 D1 00 26 00 3B 00 05 00 3B 00 0D 01 4E
         00 27 00 3B 00 05 00 3B 00 0D 01 4E 00 28 00 3B
         00 05 00 3B 00 0D 01 4E 00 29 00 3C 00 0D 00 3C
         00 13 02 D2 00 2A 00 3C 00 17 00 3C 00 18 02 D3
         00 2C 00 3C 00 0D 00 3C 00 18 01 50 00 2F 00 3D
         00 06 00 3D 00 0C 02 D4 00 30 00 3D 00 04 00 3D
         00 0C 01 54 00 31 00 3D 00 04 00 3D 00 0C 01 54
         00 32 00 3D 00 04 00 3D 00 0C 01 54 00 33 00 3F
         00 04 00 3F 00 0A 02 D5 00 34 00 3F 00 0D 00 3F
         00 0D 02 D6 00 35 00 3F 00 04 00 3F 00 0D 01 57
         00 36 00 3F 00 04 00 3F 00 0D 01 57 00 37 00 40
         00 04 00 40 00 0A 02 D7 00 38 00 40 00 0D 00 40
         00 0D 02 D8 00 39 00 40 00 04 00 40 00 0D 01 5B
         00 3A 00 40 00 04 00 40 00 0D 01 5B 00 3B 00 41
         00 04 00 41 00 0A 02 D9 00 3C 00 41 00 0D 00 41
         00 0D 02 DA 00 3D 00 41 00 04 00 41 00 0D 01 5F
         00 3E 00 41 00 04 00 41 00 0D 01 5F 00 3F 00 42
         00 04 00 42 00 0A 02 DB 00 40 00 42 00 0D 00 42
         00 0D 02 DC 00 41 00 42 00 04 00 42 00 0D 01 63
         00 42 00 42 00 04 00 42 00 0D 01 63 00 43 00 44
         00 1B 00 44 00 2B 01 71 00 46 00 44 00 1B 00 44
         00 2B 01 71 00 47 00 44 00 1B 00 44 00 2B 01 71
         00 4A 00 44 00 17 00 44 00 2B 01 6E 00 4C 00 46
         00 11 00 46 00 15 02 DD 00 4D 00 46 00 04 00 48
         00 04 01 7A 00 4F 00 46 00 04 00 48 00 04 01 7A
         00 50 00 46 00 04 00 48 00 04 01 7A 00 52 00 46
         00 04 00 48 00 04 01 7A 00 54 00 46 00 04 00 48
         00 04 01 7A 00 56 00 46 00 04 00 48 00 04 01 7A
         00 57 00 46 00 04 00 48 00 04 01 7A 00 5A 00 46
         00 04 00 48 00 04 01 7A 00 5C 00 46 00 04 00 48
         00 04 01 7A 00 5E 00 46 00 04 00 48 00 04 01 7A
         00 5F 00 46 00 04 00 48 00 04 01 7A 00 61 00 47
         00 05 00 47 00 05 02 DE 00 63 00 47 00 0B 00 47
         00 0B 02 DF 00 6B 00 47 00 05 00 47 00 0D 01 85
         00 6C 00 46 00 04 00 48 00 04 01 7A 00 72 00 4A
         00 04 00 4A 00 04 02 E0 00 82 00 4C 00 0B 00 4C
         00 11 02 E2 00 83 00 4C 00 04 00 4C 00 12 01 9A

      LocalVariableTable:
        Start  Length  Slot  Name   Signature
            0     132     0  this   LJ18;
            0     132     1 items   [I
            0     132     3 counter   I
            2      23     4     i   I
           67      65     4     m   Ljava/util/ArrayList;
           76      38     5     x   I

  public void bitwise() throws ;
    descriptor: ()V
    flags: ACC_PUBLIC
    Exceptions:
      throws
    Code:
      stack=2, locals=5, args_size=1
         0: bipush        55
         2: istore_1
         3: iload_1
         4: iconst_3
         5: ixor
         6: istore_1
         7: iload_1
         8: iconst_3
         9: ior
        10: istore_1
        11: iload_1
        12: iconst_3
        13: iand
        14: istore_1
        15: iload_1
        16: iconst_3
        17: ishl
        18: istore_1
        19: bipush        17
        21: istore_1
        22: iload_1
        23: i2d
        24: dstore_2
        25: return
      LineNumberTable:
        line 80: 0
        line 81: 3
        line 82: 7
        line 83: 11
        line 84: 15
        line 85: 19
        line 87: 22
Error: unknown attribute
        PositionTable: length = 0x120
         00 00 00 50 00 0C 00 50 00 0E 02 E3 00 02 00 50
         00 08 00 50 00 0E 01 AD 00 03 00 51 00 08 00 51
         00 08 02 E4 00 04 00 51 00 0A 00 51 00 0A 02 E5
         00 05 00 51 00 08 00 51 00 0A 01 B5 00 06 00 51
         00 04 00 51 00 0A 01 B3 00 07 00 52 00 08 00 52
         00 08 02 E6 00 08 00 52 00 0A 00 52 00 0A 02 E7
         00 09 00 52 00 08 00 52 00 0A 01 BB 00 0A 00 52
         00 04 00 52 00 0A 01 B9 00 0B 00 53 00 08 00 53
         00 08 02 E8 00 0C 00 53 00 0A 00 53 00 0A 02 E9
         00 0D 00 53 00 08 00 53 00 0A 01 C1 00 0E 00 53
         00 04 00 53 00 0A 01 BF 00 0F 00 54 00 08 00 54
         00 08 02 EA 00 10 00 54 00 0D 00 54 00 0D 02 EB
         00 11 00 54 00 08 00 54 00 0D 01 C7 00 12 00 54
         00 04 00 54 00 0D 01 C5 00 13 00 55 00 08 00 55
         00 10 02 EC 00 15 00 55 00 04 00 55 00 10 01 CB
         00 16 00 57 00 18 00 57 00 18 02 ED 00 17 00 57
         00 0F 00 57 00 18 01 D6 00 18 00 57 00 0B 00 57
         00 18 01 D3 00 19 00 4F 00 03 00 58 00 03 01 9E

      LocalVariableTable:
        Start  Length  Slot  Name   Signature
            0      26     0  this   LJ18;
            0      25     1     a   I
           22       3     2     b   D

  public boolean ifStatements() throws ;
    descriptor: ()Z
    flags: ACC_PUBLIC
    Exceptions:
      throws
    Code:
      stack=4, locals=6, args_size=1
         0: ldc           #82                 // String hello
         2: astore_2
         3: iconst_0
         4: istore_3
         5: aload_2
         6: dup
         7: astore        4
         9: invokevirtual #88                 // Method java/lang/Object.hashCode:()I
        12: lookupswitch  { // 1
                99162322: 32
                 default: 32
            }
        32: aload         4
        34: ldc           #82                 // String hello
        36: invokevirtual #91                 // Method java/lang/Object.equals:(Ljava/lang/Object;)Z
        39: ifeq          47
        42: iconst_1
        43: istore_3
        44: goto          47
        47: iload_3
        48: tableswitch   { // 0 to 1
                       0: 78
                       1: 72
                 default: 72
            }
        72: ldc           #93                 // String world
        74: astore_2
        75: goto          81
        78: goto          81
        81: aconst_null
        82: astore_3
        83: new           #97                 // class J18$InnerClass
        86: dup
        87: aload_0
        88: iconst_3
        89: invokespecial #100                // Method J18$InnerClass."<init>":(LJ18;I)V
        92: astore_3
        93: iconst_3
        94: invokestatic  #59                 // Method java/lang/Integer.valueOf:(I)Ljava/lang/Integer;
        97: astore        4
        99: goto          102
       102: iconst_1
       103: ireturn
      LineNumberTable:
        line 93: 0
        line 95: 3
        line 97: 72
        line 98: 75
        line 100: 78
        line 104: 81
        line 105: 83
        line 107: 93
        line 109: 99
        line 111: 102
        line 112: 102
Error: unknown attribute
        PositionTable: length = 0x1C8
         00 00 00 5D 00 0F 00 5D 00 15 01 EC 00 02 00 5D
         00 0B 00 5D 00 15 01 E9 00 03 00 5F 00 04 00 65
         00 04 01 EE 00 04 00 5F 00 04 00 65 00 04 01 EE
         00 05 00 5F 00 0B 00 5F 00 0B 02 EE 00 06 00 5F
         00 04 00 65 00 04 01 EE 00 07 00 5F 00 04 00 65
         00 04 01 EE 00 09 00 5F 00 04 00 65 00 04 01 EE
         00 0C 00 5F 00 04 00 65 00 04 01 EE 00 0D 00 5F
         00 04 00 65 00 04 01 EE 00 0E 00 5F 00 04 00 65
         00 04 01 EE 00 0F 00 5F 00 04 00 65 00 04 01 EE
         00 20 00 5F 00 04 00 65 00 04 01 EE 00 22 00 5F
         00 04 00 65 00 04 01 EE 00 24 00 5F 00 04 00 65
         00 04 01 EE 00 27 00 5F 00 04 00 65 00 04 01 EE
         00 2A 00 5F 00 04 00 65 00 04 01 EE 00 2B 00 5F
         00 04 00 65 00 04 01 EE 00 2F 00 5F 00 04 00 65
         00 04 01 EE 00 30 00 5F 00 04 00 65 00 04 01 EE
         00 31 00 5F 00 04 00 65 00 04 01 EE 00 32 00 5F
         00 04 00 65 00 04 01 EE 00 33 00 5F 00 04 00 65
         00 04 01 EE 00 48 00 61 00 0A 00 61 00 10 01 F7
         00 4A 00 61 00 06 00 61 00 10 01 F5 00 51 00 68
         00 14 00 68 00 17 02 05 00 52 00 68 00 0F 00 68
         00 17 02 02 00 53 00 69 00 09 00 69 00 19 02 0A
         00 56 00 69 00 09 00 69 00 19 02 0A 00 57 00 69
         00 09 00 69 00 19 02 0A 00 58 00 69 00 18 00 69
         00 18 02 EF 00 59 00 69 00 09 00 69 00 19 02 0A
         00 5C 00 69 00 04 00 69 00 19 02 08 00 5D 00 6B
         00 10 00 6B 00 10 02 F0 00 5E 00 6B 00 0C 00 6B
         00 10 02 14 00 61 00 6B 00 0C 00 6B 00 10 02 14
         00 66 00 70 00 0C 00 70 00 0F 02 37 00 67 00 70
         00 05 00 70 00 10 02 35
      LocalVariableTable:
        Start  Length  Slot  Name   Signature
            0     104     0  this   LJ18;
            0     104     2     s   Ljava/lang/String;
           81      23     3    ic   LJ18$InnerClass;
           93      11     4     a   Ljava/lang/Integer;

  public void exceptionThrower() throws java.lang.Exception;
    descriptor: ()V
    flags: ACC_PUBLIC
    Exceptions:
      throws java.lang.Exception
    Code:
      stack=4, locals=6, args_size=1
         0: iconst_2
         1: newarray       int
         3: astore_1
         4: iconst_3
         5: newarray       int
         7: dup
         8: iconst_0
         9: iconst_1
        10: iastore
        11: dup
        12: iconst_1
        13: iconst_2
        14: iastore
        15: dup
        16: iconst_2
        17: iconst_3
        18: iastore
        19: astore_2
        20: aload_1
        21: iconst_4
        22: iconst_4
        23: iastore
        24: goto          57
        27: astore        4
        29: new           #104                // class java/lang/Exception
        32: dup
        33: ldc           #106                // String A chained Exception has been thrown.
        35: invokespecial #108                // Method java/lang/Exception."<init>":(Ljava/lang/String;)V
        38: athrow
        39: astore        4
        41: aload_1
        42: iconst_0
        43: iconst_1
        44: iastore
        45: goto          57
        48: astore        4
        50: aload_1
        51: iconst_0
        52: iconst_3
        53: iastore
        54: aload         4
        56: athrow
        57: aload_1
        58: iconst_0
        59: iconst_3
        60: iastore
        61: return
      Exception table:
         from    to  target type
            20    24    27   Class java/lang/IndexOutOfBoundsException
            27    39    48   any
            20    24    39   Class java/lang/Exception
            39    48    48   any
            20    24    48   any
      LineNumberTable:
        line 120: 0
        line 121: 4
        line 122: 20
        line 123: 20
        line 124: 20
        line 126: 29
        line 128: 41
        line 130: 50
        line 130: 57
Error: unknown attribute
        PositionTable: length = 0x21C
         00 00 00 78 00 17 00 78 00 17 02 F1 00 01 00 78
         00 0F 00 78 00 18 02 54 00 03 00 78 00 0B 00 78
         00 18 02 51 00 04 00 79 00 0F 00 79 00 17 02 64
         00 05 00 79 00 0F 00 79 00 17 02 64 00 07 00 79
         00 0F 00 79 00 17 02 64 00 08 00 79 00 0F 00 79
         00 17 02 64 00 09 00 79 00 10 00 79 00 10 02 F2
         00 0A 00 79 00 0F 00 79 00 17 02 64 00 0B 00 79
         00 0F 00 79 00 17 02 64 00 0C 00 79 00 0F 00 79
         00 17 02 64 00 0D 00 79 00 13 00 79 00 13 02 F3
         00 0E 00 79 00 0F 00 79 00 17 02 64 00 0F 00 79
         00 0F 00 79 00 17 02 64 00 10 00 79 00 0F 00 79
         00 17 02 64 00 11 00 79 00 16 00 79 00 16 02 F4
         00 12 00 79 00 0F 00 79 00 17 02 64 00 13 00 79
         00 0B 00 79 00 17 02 61 00 14 00 7C 00 05 00 7C
         00 05 02 F5 00 15 00 7C 00 07 00 7C 00 07 02 F6
         00 16 00 7C 00 0C 00 7C 00 0C 02 F7 00 17 00 7C
         00 05 00 7C 00 0C 02 78 00 1B 00 7D 00 06 00 7F
         00 04 02 7F 00 1D 00 7E 00 0B 00 7E 00 3F 02 87
         00 20 00 7E 00 0B 00 7E 00 3F 02 87 00 21 00 7E
         00 19 00 7E 00 3E 02 8A 00 23 00 7E 00 0B 00 7E
         00 3F 02 87 00 26 00 7E 00 05 00 7E 00 40 02 86
         00 27 00 7F 00 06 00 81 00 04 02 8C 00 29 00 80
         00 05 00 80 00 05 02 F8 00 2A 00 80 00 07 00 80
         00 07 02 F9 00 2B 00 80 00 0C 00 80 00 0C 02 FA
         00 2C 00 80 00 05 00 80 00 0C 02 94 00 30 00 7B
         00 04 00 83 00 04 02 74 00 32 00 82 00 05 00 82
         00 05 02 FB 00 33 00 82 00 07 00 82 00 07 02 FC
         00 34 00 82 00 0C 00 82 00 0C 02 FD 00 35 00 82
         00 05 00 82 00 0C 02 FE 00 36 00 7B 00 04 00 83
         00 04 02 74 00 38 00 7B 00 04 00 83 00 04 02 74
         00 39 00 82 00 05 00 82 00 05 02 FF 00 3A 00 82
         00 07 00 82 00 07 03 00 00 3B 00 82 00 0C 00 82
         00 0C 03 01 00 3C 00 82 00 05 00 82 00 0C 02 9E
         00 3D 00 77 00 03 00 84 00 03 02 40
      LocalVariableTable:
        Start  Length  Slot  Name   Signature
            0      62     0  this   LJ18;
            0      61     1     a   [I
            4      57     2     b   [I

  static {};
    descriptor: ()V
    flags: ACC_STATIC
    Code:
      stack=1, locals=1, args_size=0
         0: ldc           #2                  // class J18
         2: invokevirtual #116                // Method java/lang/Class.desiredAssertionStatus:()Z
         5: ifne          12
         8: iconst_1
         9: goto          13
        12: iconst_0
        13: putstatic     #39                 // Field $assertiosDisabled:Z
        16: return
      LineNumberTable:
Error: unknown attribute
        PositionTable: length = 0x18
         00 0D 00 18 00 01 00 86 00 01 00 83 00 10 00 18
         00 01 00 86 00 01 00 83
      LocalVariableTable:
        Start  Length  Slot  Name   Signature
}
InnerClasses:
     #65; //class J18$1
SourceFile: "J18.java"
